{
  "openapi": "3.0.1",
  "info": {
    "title": "PokemonApi",
    "version": "1.0"
  },
  "paths": {
    "/api/pokemon/{idPokemon}/moves": {
      "get": {
        "tags": [
          "Move"
        ],
        "parameters": [
          {
            "name": "idPokemon",
            "in": "path",
            "required": true,
            "schema": {
              "type": "integer",
              "format": "int32"
            }
          }
        ],
        "responses": {
          "200": {
            "description": "OK"
          }
        }
      },
      "post": {
        "tags": [
          "Move"
        ],
        "parameters": [
          {
            "name": "idPokemon",
            "in": "path",
            "required": true,
            "schema": {
              "type": "integer",
              "format": "int32"
            }
          }
        ],
        "requestBody": {
          "content": {
            "application/json": {
              "schema": {
                "$ref": "#/components/schemas/MoveRequest"
              }
            },
            "text/json": {
              "schema": {
                "$ref": "#/components/schemas/MoveRequest"
              }
            },
            "application/*+json": {
              "schema": {
                "$ref": "#/components/schemas/MoveRequest"
              }
            }
          }
        },
        "responses": {
          "200": {
            "description": "OK"
          }
        }
      }
    },
    "/api/pokemon/{idPokemon}/moves/{idMove}": {
      "delete": {
        "tags": [
          "Move"
        ],
        "parameters": [
          {
            "name": "idPokemon",
            "in": "path",
            "required": true,
            "schema": {
              "type": "integer",
              "format": "int32"
            }
          },
          {
            "name": "idMove",
            "in": "path",
            "required": true,
            "schema": {
              "type": "integer",
              "format": "int32"
            }
          }
        ],
        "responses": {
          "200": {
            "description": "OK"
          }
        }
      }
    },
    "/api/pokemon": {
      "get": {
        "tags": [
          "Pokemon"
        ],
        "responses": {
          "200": {
            "description": "OK"
          }
        }
      },
      "post": {
        "tags": [
          "Pokemon"
        ],
        "requestBody": {
          "content": {
            "application/json": {
              "schema": {
                "$ref": "#/components/schemas/PokemonRequest"
              }
            },
            "text/json": {
              "schema": {
                "$ref": "#/components/schemas/PokemonRequest"
              }
            },
            "application/*+json": {
              "schema": {
                "$ref": "#/components/schemas/PokemonRequest"
              }
            }
          }
        },
        "responses": {
          "200": {
            "description": "OK"
          }
        }
      }
    },
    "/api/pokemon/{id}": {
      "get": {
        "tags": [
          "Pokemon"
        ],
        "parameters": [
          {
            "name": "id",
            "in": "path",
            "required": true,
            "schema": {
              "type": "integer",
              "format": "int32"
            }
          }
        ],
        "responses": {
          "200": {
            "description": "OK"
          }
        }
      },
      "put": {
        "tags": [
          "Pokemon"
        ],
        "parameters": [
          {
            "name": "id",
            "in": "path",
            "required": true,
            "schema": {
              "type": "integer",
              "format": "int32"
            }
          }
        ],
        "requestBody": {
          "content": {
            "application/json": {
              "schema": {
                "$ref": "#/components/schemas/PokemonRequest"
              }
            },
            "text/json": {
              "schema": {
                "$ref": "#/components/schemas/PokemonRequest"
              }
            },
            "application/*+json": {
              "schema": {
                "$ref": "#/components/schemas/PokemonRequest"
              }
            }
          }
        },
        "responses": {
          "200": {
            "description": "OK"
          }
        }
      },
      "delete": {
        "tags": [
          "Pokemon"
        ],
        "parameters": [
          {
            "name": "id",
            "in": "path",
            "required": true,
            "schema": {
              "type": "integer",
              "format": "int32"
            }
          }
        ],
        "responses": {
          "200": {
            "description": "OK"
          }
        }
      }
    },
    "/api/tipe": {
      "get": {
        "tags": [
          "Tipe"
        ],
        "responses": {
          "200": {
            "description": "OK"
          }
        }
      }
    },
    "/WeatherForecast": {
      "get": {
        "tags": [
          "WeatherForecast"
        ],
        "operationId": "GetWeatherForecast",
        "responses": {
          "200": {
            "description": "OK",
            "content": {
              "text/plain": {
                "schema": {
                  "type": "array",
                  "items": {
                    "$ref": "#/components/schemas/WeatherForecast"
                  }
                }
              },
              "application/json": {
                "schema": {
                  "type": "array",
                  "items": {
                    "$ref": "#/components/schemas/WeatherForecast"
                  }
                }
              },
              "text/json": {
                "schema": {
                  "type": "array",
                  "items": {
                    "$ref": "#/components/schemas/WeatherForecast"
                  }
                }
              }
            }
          }
        }
      }
    }
  },
  "components": {
    "schemas": {
      "MoveRequest": {
        "type": "object",
        "properties": {
          "id_pokemon": {
            "type": "integer",
            "format": "int32"
          },
          "nama_move": {
            "type": "string",
            "nullable": true
          },
          "power": {
            "type": "integer",
            "format": "int32"
          }
        },
        "additionalProperties": false
      },
      "PokemonRequest": {
        "type": "object",
        "properties": {
          "nama": {
            "type": "string",
            "nullable": true
          },
          "id_tipe": {
            "type": "integer",
            "format": "int32"
          },
          "level": {
            "type": "integer",
            "format": "int32"
          },
          "hp": {
            "type": "integer",
            "format": "int32"
          }
        },
        "additionalProperties": false
      },
      "WeatherForecast": {
        "type": "object",
        "properties": {
          "date": {
            "type": "string",
            "format": "date"
          },
          "temperatureC": {
            "type": "integer",
            "format": "int32"
          },
          "temperatureF": {
            "type": "integer",
            "format": "int32",
            "readOnly": true
          },
          "summary": {
            "type": "string",
            "nullable": true
          }
        },
        "additionalProperties": false
      }
    }
  }
}